deletionSort/__init__.py
deletionSort/deletionSort.py
DeletionSort-0.0.18.dist-info/METADATA
DeletionSort-0.0.18.dist-info/WHEEL
DeletionSort-0.0.18.dist-info/top_level.txt
DeletionSort-0.0.18.dist-info/RECORD
