Metadata-Version: 2.1
Name: DeletionSort
Version: 0.0.18
Summary: Deletion Sort Algorithm package
Author: HashScripts (Hashim Almuqbel)
Author-email: <hashimownemail@gmail.com>
Keywords: python,sorting,algorithm,deletion sort,sorting algorithms,O(1)
Classifier: Development Status :: 1 - Planning
Classifier: Intended Audience :: Developers
Classifier: Programming Language :: Python :: 3
Classifier: Operating System :: Unix
Classifier: Operating System :: MacOS :: MacOS X
Classifier: Operating System :: Microsoft :: Windows
